igloohome_api/__init__.py
igloohome_api-0.1.0.dist-info/METADATA
igloohome_api-0.1.0.dist-info/WHEEL
igloohome_api-0.1.0.dist-info/licenses/LICENSE
igloohome_api-0.1.0.dist-info/RECORD
