Metadata-Version: 2.4
Name: igloohome-api
Version: 0.1.0
Summary: A python package for using igloohome's API
Project-URL: Homepage, https://github.com/keithle888/igloohome-api
Project-URL: Issues, https://github.com/keithle888/igloohome-api/issues
Author-email: keithle888 <keithle888@gmail.com>
License-File: LICENSE
Classifier: License :: OSI Approved :: MIT License
Classifier: Operating System :: OS Independent
Classifier: Programming Language :: Python :: 3
Requires-Python: >=3.8
Requires-Dist: aiohttp~=3.11.10
Requires-Dist: dacite~=1.8.1
Requires-Dist: pyjwt~=2.10.1
